FireEye/FireEye.py
FireEye/__init__.py
FireEye/py_tester.py
FireEye-0.5.1.dist-info/LICENSE
FireEye-0.5.1.dist-info/METADATA
FireEye-0.5.1.dist-info/WHEEL
FireEye-0.5.1.dist-info/top_level.txt
FireEye-0.5.1.dist-info/RECORD
